{
	"info": {
		"_postman_id": "a5c814b9-14f1-4f2b-a38c-e2c1a42fdb76",
		"name": "Invoice_Consultas",
		"schema": "https://schema.getpostman.com/json/collection/v2.1.0/collection.json",
		"_exporter_id": "30579600"
	},
	"item": [
		{
			"name": "GetInvoice",
			"request": {
				"method": "GET",
				"header": [],
				"url": {
					"raw": "http://localhost:8081/invoice",
					"protocol": "http",
					"host": [
						"localhost"
					],
					"port": "8081",
					"path": [
						"invoice"
					]
				}
			},
			"response": []
		},
		{
			"name": "PostInvoice",
			"request": {
				"method": "POST",
				"header": [],
				"body": {
					"mode": "raw",
					"raw": "{\r\n    \"code\":\"777-888\",\r\n    \"create_at\": \"2023-11-25T20:45:58Z\",\r\n    \"total\":263.99,\r\n    \"client_id\":6\r\n}",
					"options": {
						"raw": {
							"language": "json"
						}
					}
				},
				"url": {
					"raw": "http://localhost:8081/invoice",
					"protocol": "http",
					"host": [
						"localhost"
					],
					"port": "8081",
					"path": [
						"invoice"
					]
				}
			},
			"response": []
		},
		{
			"name": "PutInvoice",
			"request": {
				"method": "PUT",
				"header": [],
				"body": {
					"mode": "raw",
					"raw": " {\r\n        \"id\": 3,\r\n        \"code\": \"333-444\",\r\n        \"create_at\": \"2023-11-25T20:45:58\",\r\n        \"total\": 100.99,\r\n        \"client\": 3,\r\n        \"details\": []\r\n    }",
					"options": {
						"raw": {
							"language": "json"
						}
					}
				},
				"url": {
					"raw": "http://localhost:8081/invoice",
					"protocol": "http",
					"host": [
						"localhost"
					],
					"port": "8081",
					"path": [
						"invoice"
					]
				}
			},
			"response": []
		},
		{
			"name": "New Request",
			"request": {
				"method": "PATCH",
				"header": [],
				"body": {
					"mode": "raw",
					"raw": "{\r\n    \"id\":6,\r\n    \"total\":100.99\r\n}",
					"options": {
						"raw": {
							"language": "json"
						}
					}
				},
				"url": {
					"raw": "http://localhost:8081/invoice",
					"protocol": "http",
					"host": [
						"localhost"
					],
					"port": "8081",
					"path": [
						"invoice"
					]
				}
			},
			"response": []
		},
		{
			"name": "DeleteInvoice",
			"request": {
				"method": "DELETE",
				"header": [],
				"url": {
					"raw": "http://localhost:8081/invoice/invoice/2",
					"protocol": "http",
					"host": [
						"localhost"
					],
					"port": "8081",
					"path": [
						"invoice",
						"invoice",
						"2"
					]
				}
			},
			"response": []
		}
	]
}